zoltraak/README.md
zoltraak/__init__.py
zoltraak/cli.py
zoltraak/converter.py
zoltraak/gencode.py
zoltraak/gencodebase.py
zoltraak/md_generator.py
zoltraak/requirements.txt
zoltraak/settings.py
zoltraak/setup.py
zoltraak/grimoires/architect/architect.md
zoltraak/grimoires/architect/architect_claude.md
zoltraak/grimoires/architect/architect_daiagrams.md
zoltraak/grimoires/architect/architect_detail.md
zoltraak/grimoires/architect/architect_detail_dir.md
zoltraak/grimoires/architect/architect_develop.md
zoltraak/grimoires/architect/architect_functor.md
zoltraak/grimoires/compiler/biz_consult copy.md
zoltraak/grimoires/compiler/biz_consult.md
zoltraak/grimoires/compiler/book_lecture_main.md
zoltraak/grimoires/compiler/book_lecture_quiz.md
zoltraak/grimoires/compiler/dev_akirapp.md
zoltraak/grimoires/compiler/dev_aws.md
zoltraak/grimoires/compiler/dev_front.md
zoltraak/grimoires/compiler/dev_func.md
zoltraak/grimoires/compiler/dev_obj.md
zoltraak/grimoires/compiler/dev_obj_lisp.md
zoltraak/grimoires/compiler/dev_obj_lisp_g.md
zoltraak/grimoires/compiler/dev_obj_lisp_g_base64.md
zoltraak/grimoires/compiler/dev_obj_mermaid.md
zoltraak/grimoires/compiler/dev_pypi.md
zoltraak/grimoires/compiler/dev_react_fastapi.md
zoltraak/grimoires/compiler/dev_reveal_rite.md
zoltraak/grimoires/compiler/dev_reveal_strict.md
zoltraak/grimoires/compiler/dev_streamlit.md
zoltraak/grimoires/compiler/dev_streamlit_mini.md
zoltraak/grimoires/compiler/encode_lisp.md
zoltraak/grimoires/compiler/front_faq.md
zoltraak/grimoires/compiler/front_hp.md
zoltraak/grimoires/compiler/general_def.md
zoltraak/grimoires/compiler/general_reqdef.md
zoltraak/grimoires/compiler/ref_create_directory.py
zoltraak/grimoires/developer/dev_csharp.md
zoltraak/grimoires/developer/dev_python.md
zoltraak/grimoires/encryption/emoji.md
zoltraak/grimoires/formatter/md_comment.md
zoltraak/grimoires/formatter/md_comment_ar.md
zoltraak/grimoires/formatter/md_comment_bn.md
zoltraak/grimoires/formatter/md_comment_de.md
zoltraak-0.1.37.dist-info/LICENSE
zoltraak-0.1.37.dist-info/METADATA
zoltraak-0.1.37.dist-info/WHEEL
zoltraak-0.1.37.dist-info/entry_points.txt
zoltraak-0.1.37.dist-info/top_level.txt
zoltraak-0.1.37.dist-info/RECORD
