Metadata-Version: 2.1
Name: zoltraak
Version: 0.1.37
License-File: LICENSE
Requires-Dist: openai
Requires-Dist: anthropic
Requires-Dist: groq
Requires-Dist: python-dotenv
Requires-Dist: pyperclip
Requires-Dist: wheel
Requires-Dist: diagrams
Requires-Dist: google-api-python-client
Requires-Dist: google-generativeai
